bfast_ray/__init__.py
bfast_ray/base.py
bfast_ray/bfast_ray.py
bfast_ray/monitor/__init__.py
bfast_ray/monitor/utils.py
bfast_ray/monitor/python/__init__.py
bfast_ray/monitor/python/base.py
bfast_ray-0.0.4.dist-info/LICENSE
bfast_ray-0.0.4.dist-info/METADATA
bfast_ray-0.0.4.dist-info/WHEEL
bfast_ray-0.0.4.dist-info/dependency_links.txt
bfast_ray-0.0.4.dist-info/top_level.txt
bfast_ray-0.0.4.dist-info/RECORD
