Metadata-Version: 2.1
Name: bfast-ray
Version: 0.0.4
Summary: The bfast-ray package provides a highly-efficient parallel implementation for the `Breaks For Additive Season and Trend (BFASTmonitor) proposed by Verbesselt et al. The implementation is based on Ray
Home-page: https://github.com/benerain/bfast-ray
Author: Yujia LI
Author-email: diana_15926479126@icloud.com
License: MIT license
Keywords: bfast_ray
Classifier: Intended Audience :: Developers
Classifier: License :: OSI Approved :: MIT License
Classifier: Natural Language :: English
Classifier: Programming Language :: Python :: 3
Classifier: Programming Language :: Python :: 3.8
Classifier: Programming Language :: Python :: 3.9
Classifier: Programming Language :: Python :: 3.10
Classifier: Programming Language :: Python :: 3.11
Requires-Python: >=3.8
License-File: LICENSE
Requires-Dist: numpy ==1.25.2
Requires-Dist: pandas ==2.0.3
Requires-Dist: scikit-learn ==1.3.0
Requires-Dist: scipy ==1.11.2
Requires-Dist: matplotlib ==3.7.2
Requires-Dist: wget ==3.2
Requires-Dist: ray ==2.6.1
